MOBSTERm/BoundedPareto.py
MOBSTERm/__init__.py
MOBSTERm/create_beta_pareto_dataset.py
MOBSTERm/model_mobster.py
MOBSTERm/plot_functions.py
MOBSTERm-0.1.2.dist-info/LICENSE
MOBSTERm-0.1.2.dist-info/METADATA
MOBSTERm-0.1.2.dist-info/WHEEL
MOBSTERm-0.1.2.dist-info/top_level.txt
MOBSTERm-0.1.2.dist-info/RECORD
